zebr0_lxd/__init__.py
zebr0_lxd-0.9.0.data/scripts/zebr0-lxd
zebr0_lxd-0.9.0.dist-info/LICENSE
zebr0_lxd-0.9.0.dist-info/METADATA
zebr0_lxd-0.9.0.dist-info/WHEEL
zebr0_lxd-0.9.0.dist-info/top_level.txt
zebr0_lxd-0.9.0.dist-info/RECORD
