Metadata-Version: 2.1
Name: zebr0-lxd
Version: 0.9.0
Summary: LXD provisioning based on zebr0 key-value system
Home-page: https://zebr0.io
Author: Thomas JOUANNOT
Author-email: mazerty@gmail.com
License: MIT
Download-URL: https://github.com/zebr0/zebr0-lxd
Platform: UNKNOWN
Classifier: Development Status :: 4 - Beta
Classifier: Environment :: Console
Classifier: Intended Audience :: Developers
Classifier: Intended Audience :: Information Technology
Classifier: Intended Audience :: System Administrators
Classifier: License :: OSI Approved :: MIT License
Classifier: Natural Language :: English
Classifier: Operating System :: POSIX
Classifier: Programming Language :: Python :: 3
Classifier: Topic :: System
License-File: LICENSE
Requires-Dist: zebr0
Requires-Dist: PyYAML
Requires-Dist: requests-unixsocket
